{
  "11": "Thành phố Hà Nội",
  "12": "Thành phố Hồ Chí Minh",
  "13": "Thành phố Đà Nẵng",
  "14": "Thành phố Hải Phòng",
  "15": "Thành phố Cần Thơ",
  "16": "Thành phố Huế",
  "17": "Tỉnh An Giang",
  "18": "Tỉnh Bắc Ninh",
  "19": "Tỉnh Cà Mau",
  "20": "Tỉnh Cao Bằng",
  "21": "Tỉnh Đắk Lắk",
  "22": "Tỉnh Điện Biên",
  "23": "Tỉnh Đồng Nai",
  "24": "Tỉnh Đồng Tháp",
  "25": "Tỉnh Gia Lai",
  "26": "Tỉnh Hà Tĩnh",
  "27": "Tỉnh Hưng Yên",
  "28": "Tỉnh Khánh Hòa",
  "29": "Tỉnh Lai Châu",
  "30": "Tỉnh Lâm Đồng",
  "31": "Tỉnh Lạng Sơn",
  "32": "Tỉnh Lào Cai",
  "33": "Tỉnh Nghệ An",
  "34": "Tỉnh Ninh Bình",
  "35": "Tỉnh Phú Thọ",
  "36": "Tỉnh Quảng Ngãi",
  "37": "Tỉnh Quảng Ninh",
  "38": "Tỉnh Quảng Trị",
  "39": "Tỉnh Sơn La",
  "40": "Tỉnh Tây Ninh",
  "41": "Tỉnh Thái Nguyên",
  "42": "Tỉnh Thanh Hóa",
  "43": "Tỉnh Tuyên Quang",
  "44": "Tỉnh Vĩnh Long"
}